chart_of_accounts_client-0.0.15.dist-info/DESCRIPTION.rst
chart_of_accounts_client-0.0.15.dist-info/METADATA
chart_of_accounts_client-0.0.15.dist-info/RECORD
chart_of_accounts_client-0.0.15.dist-info/WHEEL
chart_of_accounts_client-0.0.15.dist-info/metadata.json
chart_of_accounts_client-0.0.15.dist-info/top_level.txt
coa_client/__init__.py
coa_client/account_chart.py
coa_client/client.py
coa_client/config.py
coa_client/controller.py
coa_client/util.py
