Metadata-Version: 2.0
Name: chart-of-accounts-client
Version: 0.0.15
Summary: Chart of accounts client
Home-page: UNKNOWN
Author: UNKNOWN
Author-email: UNKNOWN
License: UNKNOWN
Platform: UNKNOWN
Requires-Dist: requests
Requires-Dist: cacheout
